BinConverter/BinConverterGUI.py
BinConverter/__init__.py
BinConverter/__main__.py
BinConverter/setup.py
BinConverter/core/AddSessions.py
BinConverter/core/ConversionFunctions.py
BinConverter/core/ConvertTetrode.py
BinConverter/core/CreateEEG.py
BinConverter/core/CreatePos.py
BinConverter/core/Tint_Matlab.py
BinConverter/core/__init__.py
BinConverter/core/conversion_utils.py
BinConverter/core/defaultParameters.py
BinConverter/core/filtering.py
BinConverter/core/readBin.py
BinConverter/core/utils.py
BinConverter/img/GEBA_Logo.png
BinConverter/img/__init__.py
BinConverter-1.0.4.dist-info/LICENSE
BinConverter-1.0.4.dist-info/METADATA
BinConverter-1.0.4.dist-info/WHEEL
BinConverter-1.0.4.dist-info/top_level.txt
BinConverter-1.0.4.dist-info/RECORD
