Metadata-Version: 2.1
Name: BinConverter
Version: 1.0.4
Summary: BinConverter - GUI that will allow the user to convert the raw (.bin) files from Axona's Tint software to their normal Tint format
Home-page: https://github.com/HussainiLab/BinConverter.git
Author: Geoffrey Barrett
Author-email: geoffrey.m.barrett@gmail.com
License: UNKNOWN
Platform: UNKNOWN
Classifier: Programming Language :: Python :: 3.7 
Classifier: License :: OSI Approved :: GNU General Public License v3 (GPLv3) 
Classifier: Operating System :: OS Independent
Requires-Dist: PyQt5
Requires-Dist: BatchTINTV3
Requires-Dist: numpy
Requires-Dist: scipy
